brosh/__version__.py
brosh-1.4.7.dist-info/METADATA
brosh-1.4.7.dist-info/WHEEL
brosh-1.4.7.dist-info/entry_points.txt
brosh-1.4.7.dist-info/licenses/LICENSE
brosh-1.4.7.dist-info/RECORD
