Metadata-Version: 2.4
Name: brosh
Version: 1.4.7
Summary: Browser screenshot tool using Playwright async API
Project-URL: Documentation, https://github.com/twardoch/brosh#readme
Project-URL: Issues, https://github.com/twardoch/brosh/issues
Project-URL: Source, https://github.com/twardoch/brosh
Author-email: Adam Twardoch <adam+github@twardoch.com>
License: MIT
License-File: LICENSE
Keywords: automation,browser,capture,mcp,playwright,screenshot,web
Classifier: Development Status :: 4 - Beta
Classifier: Intended Audience :: Developers
Classifier: License :: OSI Approved :: MIT License
Classifier: Operating System :: OS Independent
Classifier: Programming Language :: Python
Classifier: Programming Language :: Python :: 3.10
Classifier: Programming Language :: Python :: 3.11
Classifier: Programming Language :: Python :: 3.12
Classifier: Programming Language :: Python :: Implementation :: CPython
Classifier: Programming Language :: Python :: Implementation :: PyPy
Requires-Python: >=3.10
Requires-Dist: fastmcp>=2.8.0
Requires-Dist: fire>=0.5.0
Requires-Dist: html2text>=2025.4.15
Requires-Dist: loguru>=0.7.0
Requires-Dist: pillow>=11.2.1
Requires-Dist: platformdirs>=4.0.0
Requires-Dist: playwright>=1.40.0
Requires-Dist: pyoxipng>=9.1.0
Provides-Extra: all
Provides-Extra: dev
Requires-Dist: absolufy-imports>=0.3.1; extra == 'dev'
Requires-Dist: isort>=6.0.1; extra == 'dev'
Requires-Dist: mypy>=1.15.0; extra == 'dev'
Requires-Dist: pre-commit>=4.1.0; extra == 'dev'
Requires-Dist: pyupgrade>=3.19.1; extra == 'dev'
Requires-Dist: ruff>=0.9.7; extra == 'dev'
Requires-Dist: uzpy>=1.0.0; extra == 'dev'
Provides-Extra: docs
Requires-Dist: myst-parser<4; extra == 'docs'
Requires-Dist: sphinx-autodoc-typehints<3; extra == 'docs'
Requires-Dist: sphinx-rtd-theme>=3.0.2; extra == 'docs'
Requires-Dist: sphinx<8; extra == 'docs'
Provides-Extra: test
Requires-Dist: coverage[toml]>=7.6.12; extra == 'test'
Requires-Dist: pytest-asyncio>=1.0.0; extra == 'test'
Requires-Dist: pytest-benchmark[histogram]>=5.1.0; extra == 'test'
Requires-Dist: pytest-cov==5.0.0; extra == 'test'
Requires-Dist: pytest-xdist>=3.6.1; extra == 'test'
Requires-Dist: pytest>=8.3.4; extra == 'test'
